{
    "siteCount": 27830,
    "recentlyMoved": [
        {
            "domain_name": "noakesplugins.com",
            "destination": "Bluehost",
            "date": "2024-12-12 15:24:04"
        },
        {
            "domain_name": "vcadentistry.com",
            "destination": "Kinsta",
            "date": "2024-12-12 15:20:41"
        },
        {
            "domain_name": "everlastflooringct.com",
            "destination": "Hostinger",
            "date": "2024-12-12 15:12:20"
        },
        {
            "domain_name": "exocrossgame.com",
            "destination": "Kinsta",
            "date": "2024-12-12 15:10:11"
        },
        {
            "domain_name": "myaffinitymedspa.com",
            "destination": "Namecheap",
            "date": "2024-12-12 15:06:10"
        },
        {
            "domain_name": "equinepartnership.ie",
            "destination": "SiteGround",
            "date": "2024-12-12 14:48:03"
        },
        {
            "domain_name": "epicpestcontrol.ca",
            "destination": "Pressable",
            "date": "2024-12-12 14:45:00"
        },
        {
            "domain_name": "unityhomes.com",
            "destination": "Kinsta",
            "date": "2024-12-12 14:25:06"
        },
        {
            "domain_name": "www.wellnessdentalllc.com",
            "destination": "Kinsta",
            "date": "2024-12-12 14:23:42"
        },
        {
            "domain_name": "thefriendsofgagepark.ca",
            "destination": "Pressable",
            "date": "2024-12-12 14:22:30"
        },
        {
            "domain_name": "crossfitlevo.com",
            "destination": "Digital Ocean",
            "date": "2024-12-12 14:19:09"
        },
        {
            "domain_name": "crosscountrybattery.com",
            "destination": "Pressable",
            "date": "2024-12-12 14:19:09"
        },
        {
            "domain_name": "drlisatnd.com",
            "destination": "Pressable",
            "date": "2024-12-12 14:14:34"
        },
        {
            "domain_name": "discoveralbania.al",
            "destination": "Bluehost",
            "date": "2024-12-12 14:10:26"
        },
        {
            "domain_name": "www.smilesbydesign4u.com",
            "destination": "Kinsta",
            "date": "2024-12-12 14:03:16"
        },
        {
            "domain_name": "www.oldtownalexandrialiving.com",
            "destination": "Kinsta",
            "date": "2024-12-12 14:02:23"
        },
        {
            "domain_name": "deals.quimbysrestaurantandbar.com",
            "destination": "Liquid Web",
            "date": "2024-12-12 14:00:56"
        },
        {
            "domain_name": "sorbis.com",
            "destination": "Kinsta",
            "date": "2024-12-12 13:52:30"
        },
        {
            "domain_name": "stcatharinesdentist.ca",
            "destination": "Pressable",
            "date": "2024-12-12 13:52:14"
        },
        {
            "domain_name": "www.nadeaureid.com",
            "destination": "Kinsta",
            "date": "2024-12-12 13:49:00"
        },
        {
            "domain_name": "creativeorganics.com",
            "destination": "Pressable",
            "date": "2024-12-12 13:46:51"
        },
        {
            "domain_name": "centralpandh.ca",
            "destination": "Pressable",
            "date": "2024-12-12 13:34:36"
        },
        {
            "domain_name": "careandcurepharmacies.com",
            "destination": "Pressable",
            "date": "2024-12-12 13:30:31"
        },
        {
            "domain_name": "invoiceem.com",
            "destination": "Bluehost",
            "date": "2024-12-12 13:19:27"
        },
        {
            "domain_name": "burlingtonmedispa.ca",
            "destination": "Pressable",
            "date": "2024-12-12 13:13:51"
        },
        {
            "domain_name": "claytonbookrealty.com",
            "destination": "Kinsta",
            "date": "2024-12-12 13:10:39"
        },
        {
            "domain_name": "silicoatroofing.com",
            "destination": "DreamHost",
            "date": "2024-12-12 13:10:26"
        },
        {
            "domain_name": "boxhillswimteam.com",
            "destination": "Hostinger",
            "date": "2024-12-12 13:10:10"
        },
        {
            "domain_name": "risinglegendsaf.com",
            "destination": "Digital Ocean",
            "date": "2024-12-12 13:07:45"
        },
        {
            "domain_name": "bkkab.se",
            "destination": "GridPane",
            "date": "2024-12-12 13:05:35"
        },
        {
            "domain_name": "caroline-rochford.com",
            "destination": "SiteGround",
            "date": "2024-12-12 13:04:22"
        },
        {
            "domain_name": "insomniacpodcast.com",
            "destination": "Digital Ocean",
            "date": "2024-12-12 13:00:42"
        },
        {
            "domain_name": "www.davidcoffey.ca",
            "destination": "Kinsta",
            "date": "2024-12-12 12:58:18"
        },
        {
            "domain_name": "sevencrownstattoo.com",
            "destination": "Kinsta",
            "date": "2024-12-12 12:47:05"
        },
        {
            "domain_name": "qtdental.com",
            "destination": "Kinsta",
            "date": "2024-12-12 12:44:35"
        },
        {
            "domain_name": "asimebrahimi.com",
            "destination": "Kinsta",
            "date": "2024-12-12 12:42:20"
        },
        {
            "domain_name": "bbmbusiness.com",
            "destination": "Pressable",
            "date": "2024-12-12 12:34:53"
        },
        {
            "domain_name": "ancasterelectric.ca",
            "destination": "Pressable",
            "date": "2024-12-12 12:25:48"
        },
        {
            "domain_name": "realestateokotoks.com",
            "destination": "Kinsta",
            "date": "2024-12-12 12:24:43"
        },
        {
            "domain_name": "berniceranalli.ca",
            "destination": "Pressable",
            "date": "2024-12-12 12:20:13"
        },
        {
            "domain_name": "prairielakesfamilydentistry.com",
            "destination": "Kinsta",
            "date": "2024-12-12 12:17:25"
        },
        {
            "domain_name": "www.chipbarkel.com",
            "destination": "Kinsta",
            "date": "2024-12-12 12:11:35"
        },
        {
            "domain_name": "principles.fish",
            "destination": "GoDaddy",
            "date": "2024-12-12 12:09:37"
        },
        {
            "domain_name": "www.activekidsadventurepark.co.uk",
            "destination": "Kinsta",
            "date": "2024-12-12 11:58:53"
        },
        {
            "domain_name": "www.santaclaraendodontics.com",
            "destination": "Kinsta",
            "date": "2024-12-12 11:53:59"
        },
        {
            "domain_name": "www.drjepko.com",
            "destination": "Kinsta",
            "date": "2024-12-12 11:52:39"
        },
        {
            "domain_name": "plgdelivers.com",
            "destination": "BigScoots",
            "date": "2024-12-12 11:47:44"
        },
        {
            "domain_name": "417travel.com",
            "destination": "SiteGround",
            "date": "2024-12-12 11:43:18"
        },
        {
            "domain_name": "partnersinart.ca",
            "destination": "GoDaddy",
            "date": "2024-12-12 11:41:58"
        },
        {
            "domain_name": "womensfundmiami.org",
            "destination": "Pressable",
            "date": "2024-12-12 11:33:50"
        },
        {
            "domain_name": "pagosadentalimplantcenter.com",
            "destination": "Kinsta",
            "date": "2024-12-12 11:24:37"
        },
        {
            "domain_name": "faith4lifeaus.com",
            "destination": "DreamHost",
            "date": "2024-12-12 11:00:39"
        },
        {
            "domain_name": "brothernarms.com",
            "destination": "HostGator",
            "date": "2024-12-12 09:20:30"
        },
        {
            "domain_name": "busturnaround.nyc",
            "destination": "Hostinger",
            "date": "2024-12-12 09:12:00"
        },
        {
            "domain_name": "jescraft.com",
            "destination": "Pressable",
            "date": "2024-12-12 09:11:37"
        },
        {
            "domain_name": "broadstreetprivateequity.com",
            "destination": "Pressable",
            "date": "2024-12-12 08:56:22"
        },
        {
            "domain_name": "headfordonline.ie",
            "destination": "Kinsta",
            "date": "2024-12-12 08:40:33"
        },
        {
            "domain_name": "heygolfguide.se",
            "destination": "Pressable",
            "date": "2024-12-12 08:36:31"
        },
        {
            "domain_name": "ihaveadream.org.nz",
            "destination": "SiteGround",
            "date": "2024-12-12 08:33:13"
        },
        {
            "domain_name": "ww99.pinestatedrilling.com",
            "destination": "Liquid Web",
            "date": "2024-12-12 08:07:01"
        },
        {
            "domain_name": "tracibuckphotography.com",
            "destination": "IONOS",
            "date": "2024-12-12 06:35:33"
        },
        {
            "domain_name": "dagsam.dk",
            "destination": "SiteGround",
            "date": "2024-12-12 06:19:31"
        },
        {
            "domain_name": "theflexappealwf.com",
            "destination": "Digital Ocean",
            "date": "2024-12-12 05:48:46"
        },
        {
            "domain_name": "www.seattlegardeningservice.com",
            "destination": "BigScoots",
            "date": "2024-12-12 05:28:20"
        },
        {
            "domain_name": "solarschool.se",
            "destination": "Hetzner Online",
            "date": "2024-12-12 05:02:20"
        },
        {
            "domain_name": "solarschool.no",
            "destination": "Hetzner Online",
            "date": "2024-12-12 05:02:20"
        },
        {
            "domain_name": "solarschool.dk",
            "destination": "Hetzner Online",
            "date": "2024-12-12 05:02:20"
        },
        {
            "domain_name": "smartfarm.nl",
            "destination": "Kinsta",
            "date": "2024-12-12 05:00:13"
        },
        {
            "domain_name": "greatsouthernexperiences.com.au",
            "destination": "Kinsta",
            "date": "2024-12-12 04:32:40"
        },
        {
            "domain_name": "ashlandfirst.org",
            "destination": "OVH",
            "date": "2024-12-12 04:08:22"
        },
        {
            "domain_name": "www.pearlydentalcare.com",
            "destination": "Kinsta",
            "date": "2024-12-12 03:45:24"
        },
        {
            "domain_name": "valhallaflwr.com",
            "destination": "GoDaddy",
            "date": "2024-12-12 02:51:31"
        },
        {
            "domain_name": "www.yipdds.com",
            "destination": "Kinsta",
            "date": "2024-12-12 02:41:27"
        },
        {
            "domain_name": "traveltochangetheworld.com",
            "destination": "Kinsta",
            "date": "2024-12-12 02:31:34"
        },
        {
            "domain_name": "xali.com.au",
            "destination": "Kinsta",
            "date": "2024-12-12 02:16:20"
        },
        {
            "domain_name": "www.remote.com.au",
            "destination": "Liquid Web",
            "date": "2024-12-12 01:58:41"
        },
        {
            "domain_name": "www.paschenorthodontics.com",
            "destination": "Kinsta",
            "date": "2024-12-12 01:42:52"
        },
        {
            "domain_name": "www.hardyba.com.au",
            "destination": "Kinsta",
            "date": "2024-12-12 01:10:34"
        },
        {
            "domain_name": "hormone-zone.com",
            "destination": "Namecheap",
            "date": "2024-12-12 00:42:30"
        },
        {
            "domain_name": "procladd.co.nz",
            "destination": "Digital Ocean",
            "date": "2024-12-12 00:36:25"
        },
        {
            "domain_name": "www.familybusinessmatters.consulting",
            "destination": "Pressable",
            "date": "2024-12-12 00:24:02"
        },
        {
            "domain_name": "www.bumpsforboomers.com",
            "destination": "Pressable",
            "date": "2024-12-12 00:21:14"
        },
        {
            "domain_name": "www.araleighbga.com.au",
            "destination": "Pressable",
            "date": "2024-12-12 00:07:57"
        },
        {
            "domain_name": "www.blizzardpress.com",
            "destination": "Pressable",
            "date": "2024-12-12 00:04:47"
        },
        {
            "domain_name": "prevent.co.nz",
            "destination": "Digital Ocean",
            "date": "2024-12-12 00:01:21"
        },
        {
            "domain_name": "familybusinessmatters.consulting",
            "destination": "Pressable",
            "date": "2024-12-11 23:51:28"
        },
        {
            "domain_name": "govirtualoffice.com",
            "destination": "GoDaddy",
            "date": "2024-12-11 23:44:53"
        },
        {
            "domain_name": "onlysmilesdental.com",
            "destination": "Kinsta",
            "date": "2024-12-11 23:40:54"
        },
        {
            "domain_name": "p-slegal.com.au",
            "destination": "Pressable",
            "date": "2024-12-11 23:33:48"
        },
        {
            "domain_name": "a1glassshowers.com.au",
            "destination": "SiteGround",
            "date": "2024-12-11 23:24:53"
        },
        {
            "domain_name": "ephc.net.au",
            "destination": "Pressable",
            "date": "2024-12-11 22:16:45"
        },
        {
            "domain_name": "thebeacharrawarra.com.au",
            "destination": "Kinsta",
            "date": "2024-12-11 22:12:54"
        },
        {
            "domain_name": "www.teamrealty.ca",
            "destination": "SiteGround",
            "date": "2024-12-11 22:04:25"
        },
        {
            "domain_name": "loanpartner.co.nz",
            "destination": "Digital Ocean",
            "date": "2024-12-11 21:59:27"
        },
        {
            "domain_name": "coloradocreativecorridor.com",
            "destination": "Pressable",
            "date": "2024-12-11 21:58:32"
        },
        {
            "domain_name": "drmarvinsingh.com",
            "destination": "Pressable",
            "date": "2024-12-11 21:56:45"
        },
        {
            "domain_name": "strawbridgebuild.co.nz",
            "destination": "Digital Ocean",
            "date": "2024-12-11 21:48:35"
        },
        {
            "domain_name": "www.regenezone.com",
            "destination": "Namecheap",
            "date": "2024-12-11 21:44:14"
        },
        {
            "domain_name": "www.paintnmore.com",
            "destination": "Pressable",
            "date": "2024-12-11 21:42:55"
        },
        {
            "domain_name": "solicleaning.com",
            "destination": "SiteGround",
            "date": "2024-12-11 21:21:42"
        }
    ],
    "dailyMovedStat": {
        "2024-09-21": "94",
        "2024-09-22": "199",
        "2024-09-23": "345",
        "2024-09-24": "492",
        "2024-09-25": "709",
        "2024-09-26": "920",
        "2024-09-27": "1151",
        "2024-09-28": "1378",
        "2024-09-29": "1581",
        "2024-09-30": "1808",
        "2024-10-01": "2030",
        "2024-10-02": "2247",
        "2024-10-03": "2544",
        "2024-10-04": "2807",
        "2024-10-05": "3040",
        "2024-10-06": "3176",
        "2024-10-07": "3225",
        "2024-10-08": "3236",
        "2024-10-09": "5144",
        "2024-10-10": "5833",
        "2024-10-11": "5893",
        "2024-10-12": "5998",
        "2024-10-13": "6306",
        "2024-10-14": "6505",
        "2024-10-15": "6891",
        "2024-10-16": "7295",
        "2024-10-17": "7706",
        "2024-10-18": "8159",
        "2024-10-19": "8726",
        "2024-10-20": "8887",
        "2024-10-21": "9024",
        "2024-10-22": "9363",
        "2024-10-23": "9983",
        "2024-10-24": "10540",
        "2024-10-25": "11045",
        "2024-10-26": "11549",
        "2024-10-27": "11717",
        "2024-10-28": "11903",
        "2024-10-29": "12374",
        "2024-10-30": "12971",
        "2024-10-31": "13468",
        "2024-11-01": "13969",
        "2024-11-02": "14516",
        "2024-11-03": "14627",
        "2024-11-04": "14709",
        "2024-11-05": "15080",
        "2024-11-06": "16045",
        "2024-11-07": "16446",
        "2024-11-08": "16798",
        "2024-11-09": "17121",
        "2024-11-10": "17418",
        "2024-11-11": "17860",
        "2024-11-12": "18294",
        "2024-11-13": "18512",
        "2024-11-14": "18951",
        "2024-11-15": "19435",
        "2024-11-16": "19838",
        "2024-11-17": "19924",
        "2024-11-18": "20048",
        "2024-11-19": "20351",
        "2024-11-20": "20977",
        "2024-11-21": "21733",
        "2024-11-22": "22351",
        "2024-11-23": "22794",
        "2024-11-24": "22890",
        "2024-11-25": "23102",
        "2024-11-26": "23520",
        "2024-11-27": "23890",
        "2024-11-28": "24253",
        "2024-11-29": "24507",
        "2024-11-30": "24714",
        "2024-12-01": "24827",
        "2024-12-02": "24959",
        "2024-12-03": "25264",
        "2024-12-04": "25595",
        "2024-12-05": "25980",
        "2024-12-06": "26353",
        "2024-12-07": "26706",
        "2024-12-08": "26828",
        "2024-12-09": "26944",
        "2024-12-10": "27235",
        "2024-12-11": "27669"
    },
    "topDestinationHosts": {
        "Pressable": 6317,
        "Bluehost": 3511,
        "Digital Ocean": 1733,
        "Kinsta": 1709,
        "SiteGround": 1568,
        "Hostinger": 882,
        "GoDaddy": 421,
        "BigScoots": 258,
        "Elementor Hosting": 191,
        "Liquid Web": 179,
        "Wordify": 139,
        "WordPress.com": 121,
        "InMotion Hosting": 110,
        "OVH": 97,
        "GridPane": 96,
        "A2 Hosting": 76,
        "Namecheap": 69,
        "Hetzner Online": 69,
        "IONOS": 69,
        "DreamHost": 57
    },
    "dailyTotalStat": {
        "2024-09-21": "745273",
        "2024-09-22": "744978",
        "2024-09-23": "744642",
        "2024-09-24": "744305",
        "2024-09-25": "743898",
        "2024-09-26": "743497",
        "2024-09-27": "743076",
        "2024-09-28": "742659",
        "2024-09-29": "742266",
        "2024-09-30": "741849",
        "2024-10-01": "741437",
        "2024-10-02": "741030",
        "2024-10-03": "740543",
        "2024-10-04": "740090",
        "2024-10-05": "739667",
        "2024-10-06": "739341",
        "2024-10-07": "739102",
        "2024-10-08": "738901",
        "2024-10-09": "736803",
        "2024-10-10": "735829",
        "2024-10-11": "735997",
        "2024-10-12": "735841",
        "2024-10-13": "735365",
        "2024-10-14": "734798",
        "2024-10-15": "734234",
        "2024-10-16": "733668",
        "2024-10-17": "733075",
        "2024-10-18": "732477",
        "2024-10-19": "731732",
        "2024-10-20": "731533",
        "2024-10-21": "731196",
        "2024-10-22": "730633",
        "2024-10-23": "729850",
        "2024-10-24": "729189",
        "2024-10-25": "728350",
        "2024-10-26": "727792",
        "2024-10-27": "727537",
        "2024-10-28": "727127",
        "2024-10-29": "726413",
        "2024-10-30": "725658",
        "2024-10-31": "725027",
        "2024-11-01": "724384",
        "2024-11-02": "723748",
        "2024-11-03": "723544",
        "2024-11-04": "723276",
        "2024-11-05": "722762",
        "2024-11-06": "721646",
        "2024-11-07": "721100",
        "2024-11-08": "720563",
        "2024-11-09": "720107",
        "2024-11-10": "719748",
        "2024-11-11": "719157",
        "2024-11-12": "718533",
        "2024-11-13": "718108",
        "2024-11-14": "717543",
        "2024-11-15": "716862",
        "2024-11-16": "716381",
        "2024-11-17": "716544",
        "2024-11-18": "715924",
        "2024-11-19": "715530",
        "2024-11-20": "714747",
        "2024-11-21": "712869",
        "2024-11-22": "712189",
        "2024-11-23": "711241",
        "2024-11-24": "707360",
        "2024-11-25": "707035",
        "2024-11-26": "705867",
        "2024-11-27": "704968",
        "2024-11-28": "704773",
        "2024-11-29": "704054",
        "2024-11-30": "703389",
        "2024-12-01": "704036",
        "2024-12-02": "702375",
        "2024-12-03": "701792",
        "2024-12-04": "701042",
        "2024-12-05": "696740",
        "2024-12-06": "698884",
        "2024-12-07": "698514",
        "2024-12-08": "699485",
        "2024-12-09": "698652",
        "2024-12-10": "697735",
        "2024-12-11": "696939"
    }
}